wmapi/__init__.py
wmapi/wmapi.py
wmapi-0.1.dist-info/LICENSE
wmapi-0.1.dist-info/METADATA
wmapi-0.1.dist-info/WHEEL
wmapi-0.1.dist-info/top_level.txt
wmapi-0.1.dist-info/RECORD
