Metadata-Version: 2.1
Name: wmapi
Version: 0.1
Summary: Python Client for Walmart Canada Marketplace API
Home-page: https://github.com/sellerzoncom/wmapi
Author: SellerZon
Author-email: dev@sellerzon.com
License: UNKNOWN
Platform: UNKNOWN
Classifier: Development Status :: 2 - Pre-Alpha
Classifier: Programming Language :: Python
Classifier: Programming Language :: Python :: 2
Classifier: Programming Language :: Python :: 2.7
Classifier: Programming Language :: Python :: 3
Classifier: Programming Language :: Python :: 3.4
Classifier: Programming Language :: Python :: 3.5
Requires-Dist: xmltodict
Requires-Dist: requests
